{
  "slug": "erreurs-tva",
  "title": "Erreurs de TVA dans les devis travaux : quelle fréquence ?",
  "description": "Analyse des taux de TVA appliqués sur 313 devis : 20%, 10%, 5,5%. Combien d'erreurs détectables ?",
  "lastGenerated": "2026-06-30T16:51:43.052Z",
  "totalAnalyses": 313,
  "intro": "Le taux de TVA applicable dépend du type de travaux et de l'ancienneté du logement. 20% pour le neuf et certains équipements, 10% en rénovation classique, 5,5% pour la rénovation énergétique. Voici la répartition réelle observée sur 313 devis.",
  "stats": [
    {
      "rank": 1,
      "label": "TVA 20%",
      "value": "75 devis",
      "subtitle": "24% des devis observés",
      "context": "Applicable au neuf et à certains équipements de + de 2 ans."
    },
    {
      "rank": 2,
      "label": "TVA 10%",
      "value": "126 devis",
      "subtitle": "40% des devis observés",
      "context": "Applicable en rénovation classique sur des logements > 2 ans."
    },
    {
      "rank": 3,
      "label": "TVA 5,5%",
      "value": "54 devis",
      "subtitle": "17% des devis observés",
      "context": "Applicable aux travaux d'amélioration énergétique."
    },
    {
      "rank": 4,
      "label": "TVA non standard",
      "value": "58 devis",
      "subtitle": "19% des devis observés",
      "context": "Taux différent de 20/10/5,5 — souvent une erreur d'extraction ou un devis étranger."
    },
    {
      "rank": 5,
      "label": "TVA potentiellement incohérente",
      "value": "2 devis suspects",
      "subtitle": "Mention 'rénovation' + TVA 20%",
      "context": "À ces 20% applicable, le client pourrait économiser 10 points de TVA (passage à 10% ou 5,5%)."
    }
  ],
  "methodology": "Lecture du champ extracted.totaux.taux_tva pour 313 analyses récentes. Détection d'incohérence basique : présence du mot 'rénovation' dans l'extraction + TVA 20%."
}